{
	"schemaVersion": 1,
	"id": "specifics",
	"version": "${version}",
	"name": "Specifics",
	"description": "Specific changes for the server :)\nSome textures from https://vanillatweaks.net/",
	"authors": [
		"Paul Marmet"
	],
	"contact": {
	},
	"license": "ARR",
	"icon": "assets/specifics/icon.png",
	"environment": "*",
	"entrypoints": {
		"main": [
			"net.pm.specifics.Specifics"
		]
	},
	"accessWidener" : "specifics.accesswidener",
	"mixins": [
		"specifics.mixins.json"
	],
	"depends": {
		"fabricloader": ">=0.15.11",
		"minecraft": "~1.21",
		"java": ">=21",
		"fabric-api": "*"
	}
}